{"_ts":[1541053486],"_r":{"breakdown":{"html":{"bytes":[11598],"requests":[5]},"js":{"bytes":[1011778],"requests":[24]},"css":{"bytes":[23150],"requests":[3]},"image":{"bytes":[250253],"requests":[45]},"flash":{"bytes":[0],"requests":[0]},"font":{"bytes":[95084],"requests":[4]},"video":{"bytes":[0],"requests":[0]},"other":{"bytes":[2291],"requests":[8]}},"date":[1541053486],"domElements":[710],"domInteractive":[899],"firstPaint":[868.9999999988],"fullyLoaded":[4993],"id":["181101_0R_abbfbc0db52239ab64a901025c931737"],"loadTime":[3736],"render":[800],"SpeedIndex":[973],"TTFB":[392],"videoFrames":[[{"_i":"ms_000000.jpg","_t":0,"_vc":0},{"_i":"ms_000800.jpg","_t":800,"_vc":68},{"_i":"ms_001000.jpg","_t":1000,"_vc":84},{"_i":"ms_001100.jpg","_t":1100,"_vc":84},{"_i":"ms_001200.jpg","_t":1200,"_vc":93},{"_i":"ms_001400.jpg","_t":1400,"_vc":94},{"_i":"ms_001500.jpg","_t":1500,"_vc":95},{"_i":"ms_001700.jpg","_t":1700,"_vc":98},{"_i":"ms_001900.jpg","_t":1900,"_vc":99},{"_i":"ms_002500.jpg","_t":2500,"_vc":99},{"_i":"ms_002600.jpg","_t":2600,"_vc":98},{"_i":"ms_003800.jpg","_t":3800,"_vc":98},{"_i":"ms_004200.jpg","_t":4200,"_vc":99},{"_i":"ms_004400.jpg","_t":4400,"_vc":99},{"_i":"ms_004500.jpg","_t":4500,"_vc":99},{"_i":"ms_004600.jpg","_t":4600,"_vc":100}]],"visualComplete":[4600],"lighthouse":[31],"pagespeed":[75]}}